[{"line":1,"elements":[{"start_timestamp":"2024-02-15T09:18:03.795Z","line":3,"name":"The example","description":"","id":"an-example;the-example","type":"scenario","keyword":"Scenario","steps":[{"result":{"duration":3742193400,"status":"passed"},"line":4,"name":"Add a new pet","match":{"location":"com.automation.RestAssured.StepDefinitions.Addanewpet()"},"keyword":"Given "},{"result":{"duration":1224105400,"status":"passed"},"line":5,"name":"Updates a pet in the store with the form data","match":{"location":"com.automation.RestAssured.StepDefinitions.Updatesapetinthestorewiththeformdata()"},"keyword":"When "},{"result":{"duration":1242887600,"status":"passed"},"line":6,"name":"Find Pets by status","match":{"location":"com.automation.RestAssured.StepDefinitions.FindPetsbystatus()"},"keyword":"Then "},{"result":{"duration":1189857300,"status":"passed"},"line":7,"name":"Find Pets by tags","match":{"location":"com.automation.RestAssured.StepDefinitions.FindPetsbytags()"},"keyword":"And "},{"result":{"duration":1248563400,"status":"passed"},"line":8,"name":"Find Pets by ID","match":{"location":"com.automation.RestAssured.StepDefinitions.FindPetsbyID()"},"keyword":"And "},{"result":{"duration":1184181400,"status":"passed"},"line":9,"name":"Update an existing Pet","match":{"location":"com.automation.RestAssured.StepDefinitions.UpdateanexistingPet()"},"keyword":"And "},{"result":{"duration":1152872600,"status":"passed"},"line":10,"name":"Delete the Pet","match":{"location":"com.automation.RestAssured.StepDefinitions.DeletethePet()"},"keyword":"And "}]}],"name":"An example","description":"","id":"an-example","keyword":"Feature","uri":"classpath:com/automation/RestAssured/example.feature","tags":[]}]